{
   "name":  "Query", 
   "result": 0.309676,
   "timing": 0.309676,
   "cardinality": 1,
   "extra_info": "SELECT MIN(cn.name) AS from_company,\n       MIN(mc.note) AS production_note,\n       MIN(t.title) AS movie_based_on_book\nFROM company_name AS cn,\n     company_type AS ct,\n     keyword AS k,\n     link_type AS lt,\n     movie_companies AS mc,\n     movie_keyword AS mk,\n     movie_link AS ml,\n     title AS t\nWHERE cn.country_code !='[pl]'\n  AND (cn.name LIKE '20th Century Fox%'\n       OR cn.name LIKE 'Twentieth Century Fox%')\n  AND ct.kind != 'production companies'\n  AND ct.kind IS NOT NULL\n  AND k.keyword IN ('sequel',\n                    'revenge',\n                    'based-on-novel')\n  AND mc.note IS NOT NULL\n  AND t.production_year > 1950\n  AND lt.id = ml.link_type_id\n  AND ml.movie_id = t.id\n  AND t.id = mk.movie_id\n  AND mk.keyword_id = k.id\n  AND t.id = mc.movie_id\n  AND mc.company_type_id = ct.id\n  AND mc.company_id = cn.id\n  AND ml.movie_id = mk.movie_id\n  AND ml.movie_id = mc.movie_id\n  AND mk.movie_id = mc.movie_id;", 
   "timings": [

   ],
   "children": [
    {
      "name": "SIMPLE_AGGREGATE",
      "timing":0.000258,
      "cardinality":1,
      "extra_info": "min(#0)\nmin(#1)\nmin(#2)",
      "timings": [
      ],
      "children": [
       {
         "name": "PROJECTION",
         "timing":0.000001,
         "cardinality":6946,
         "extra_info": "cn.name\nmc.note\nt.title\n",
         "timings": [
         ],
         "children": [
          {
            "name": "HASH_JOIN",
            "timing":0.000041,
            "cardinality":6946,
            "extra_info": "INNER\nmc.company_id = cn.id\n",
            "timings": [
            ],
            "children": [
             {
               "name": "HASH_JOIN",
               "timing":0.000028,
               "cardinality":14916,
               "extra_info": "INNER\nmc.company_type_id = ct.id\n",
               "timings": [
               ],
               "children": [
                {
                  "name": "HASH_JOIN",
                  "timing":0.017023,
                  "cardinality":15510,
                  "extra_info": "INNER\nmk.keyword_id = k.id\n",
                  "timings": [
                  ],
                  "children": [
                   {
                     "name": "HASH_JOIN",
                     "timing":0.007181,
                     "cardinality":3405648,
                     "extra_info": "INNER\nml.link_type_id = lt.id\n",
                     "timings": [
                     ],
                     "children": [
                      {
                        "name": "HASH_JOIN",
                        "timing":0.070907,
                        "cardinality":3405648,
                        "extra_info": "INNER\nt.id = mc.movie_id\nml.movie_id = mc.movie_id\nmk.movie_id = mc.movie_id\n",
                        "timings": [
                        ],
                        "children": [
                         {
                           "name": "HASH_JOIN",
                           "timing":0.099818,
                           "cardinality":286392,
                           "extra_info": "INNER\nmk.movie_id = t.id\nmk.movie_id = ml.movie_id\n",
                           "timings": [
                           ],
                           "children": [
                            {
                              "name": "SEQ_SCAN",
                              "timing":0.001110,
                              "cardinality":4523930,
                              "extra_info": "movie_keyword\n[INFOSEPARATOR]\nmovie_id\nkeyword_id",
                              "timings": [
                              ],
                              "children": [
                              ]
                            }
,
                            {
                              "name": "HASH_JOIN",
                              "timing":0.016115,
                              "cardinality":29726,
                              "extra_info": "INNER\nt.id = ml.movie_id\n",
                              "timings": [
                              ],
                              "children": [
                               {
                                 "name": "SEQ_SCAN",
                                 "timing":0.026273,
                                 "cardinality":2287271,
                                 "extra_info": "title\n[INFOSEPARATOR]\nproduction_year\nid\ntitle\n[INFOSEPARATOR]\nFilters: production_year>1950 AND production_year IS NOT NULL\n",
                                 "timings": [
                                 ],
                                 "children": [
                                 ]
                               }
,
                               {
                                 "name": "SEQ_SCAN",
                                 "timing":0.000007,
                                 "cardinality":29997,
                                 "extra_info": "movie_link\n[INFOSEPARATOR]\nlink_type_id\nmovie_id",
                                 "timings": [
                                 ],
                                 "children": [
                                 ]
                               }
                              ]
                            }
                           ]
                         }
,
                         {
                           "name": "FILTER",
                           "timing":0.003630,
                           "cardinality":1337140,
                           "extra_info": "(mc.note IS NOT NULL)",
                           "timings": [
                           ],
                           "children": [
                            {
                              "name": "SEQ_SCAN",
                              "timing":0.006305,
                              "cardinality":2609129,
                              "extra_info": "movie_companies\n[INFOSEPARATOR]\nnote\nmovie_id\ncompany_type_id\ncompany_id",
                              "timings": [
                              ],
                              "children": [
                              ]
                            }
                           ]
                         }
                        ]
                      }
,
                      {
                        "name": "SEQ_SCAN",
                        "timing":0.000003,
                        "cardinality":18,
                        "extra_info": "link_type\n[INFOSEPARATOR]\nid",
                        "timings": [
                        ],
                        "children": [
                        ]
                      }
                     ]
                   }
,
                   {
                     "name": "PROJECTION",
                     "timing":0.000000,
                     "cardinality":3,
                     "extra_info": "#1\n",
                     "timings": [
                     ],
                     "children": [
                      {
                        "name": "FILTER",
                        "timing":0.001820,
                        "cardinality":3,
                        "extra_info": "(k.keyword = 'sequel' OR k.keyword = 'revenge' OR k.keyword = 'based-on-novel')",
                        "timings": [
                        ],
                        "children": [
                         {
                           "name": "SEQ_SCAN",
                           "timing":0.001001,
                           "cardinality":134170,
                           "extra_info": "keyword\n[INFOSEPARATOR]\nkeyword\nid",
                           "timings": [
                           ],
                           "children": [
                           ]
                         }
                        ]
                      }
                     ]
                   }
                  ]
                }
,
                {
                  "name": "PROJECTION",
                  "timing":0.000000,
                  "cardinality":3,
                  "extra_info": "#1\n",
                  "timings": [
                  ],
                  "children": [
                   {
                     "name": "FILTER",
                     "timing":0.000002,
                     "cardinality":3,
                     "extra_info": "ct.kind != 'production companies'",
                     "timings": [
                     ],
                     "children": [
                      {
                        "name": "SEQ_SCAN",
                        "timing":0.000001,
                        "cardinality":4,
                        "extra_info": "company_type\n[INFOSEPARATOR]\nkind\nid",
                        "timings": [
                        ],
                        "children": [
                        ]
                      }
                     ]
                   }
                  ]
                }
               ]
             }
,
             {
               "name": "PROJECTION",
               "timing":0.000001,
               "cardinality":89,
               "extra_info": "#1\n#2\n",
               "timings": [
               ],
               "children": [
                {
                  "name": "FILTER",
                  "timing":0.002436,
                  "cardinality":89,
                  "extra_info": "(cn.country_code != '[pl]' AND (prefix(cn.name, '20th Century Fox') OR prefix(cn.name, 'Twentieth Century Fox')))",
                  "timings": [
                  ],
                  "children": [
                   {
                     "name": "SEQ_SCAN",
                     "timing":0.002260,
                     "cardinality":234997,
                     "extra_info": "company_name\n[INFOSEPARATOR]\ncountry_code\nname\nid",
                     "timings": [
                     ],
                     "children": [
                     ]
                   }
                  ]
                }
               ]
             }
            ]
          }
         ]
       }
      ]
    }
   ]
}